<?xml version='1.0' encoding='utf-8'?>
<annotation>
	<source>
		<filename>8579.tif</filename>
		<origin>Optical</origin>
	</source>
	<research>
		<version>1.0</version>
		<author>Cyber</author>
		<pluginclass>object detection</pluginclass>
		<time>2021-07-21</time>
	</research>
	<size>
		<width>800</width>
		<height>600</height>
		<depth>4</depth>
	</size>
	<objects>
		<object>
			<coordinate>pixel</coordinate>
			<type>rectangle</type>
			<description>None</description>
			<possibleresult>
				<name>Van</name>
			</possibleresult>
			<points>
				<point>70.000000,109.000000</point>
				<point>68.000000,125.000000</point>
				<point>59.000000,124.000000</point>
				<point>61.000000,108.000000</point>
				<point>70.000000,109.000000</point>
			</points>
		</object>
		<object>
			<coordinate>pixel</coordinate>
			<type>rectangle</type>
			<description>None</description>
			<possibleresult>
				<name>Dump Truck</name>
			</possibleresult>
			<points>
				<point>61.000000,166.000000</point>
				<point>60.000000,174.000000</point>
				<point>36.000000,171.000000</point>
				<point>36.000000,163.000000</point>
				<point>61.000000,166.000000</point>
			</points>
		</object>
		<object>
			<coordinate>pixel</coordinate>
			<type>rectangle</type>
			<description>None</description>
			<possibleresult>
				<name>Van</name>
			</possibleresult>
			<points>
				<point>61.000000,157.000000</point>
				<point>60.000000,165.000000</point>
				<point>37.000000,162.000000</point>
				<point>39.000000,154.000000</point>
				<point>61.000000,157.000000</point>
			</points>
		</object>
		<object>
			<coordinate>pixel</coordinate>
			<type>rectangle</type>
			<description>None</description>
			<possibleresult>
				<name>Small Car</name>
			</possibleresult>
			<points>
				<point>18.000000,270.000000</point>
				<point>16.000000,288.000000</point>
				<point>6.000000,286.000000</point>
				<point>8.000000,269.000000</point>
				<point>18.000000,270.000000</point>
			</points>
		</object>
		<object>
			<coordinate>pixel</coordinate>
			<type>rectangle</type>
			<description>None</description>
			<possibleresult>
				<name>Van</name>
			</possibleresult>
			<points>
				<point>31.000000,269.000000</point>
				<point>28.000000,289.000000</point>
				<point>18.000000,287.000000</point>
				<point>20.000000,268.000000</point>
				<point>31.000000,269.000000</point>
			</points>
		</object>
		<object>
			<coordinate>pixel</coordinate>
			<type>rectangle</type>
			<description>None</description>
			<possibleresult>
				<name>Small Car</name>
			</possibleresult>
			<points>
				<point>98.000000,261.000000</point>
				<point>97.000000,269.000000</point>
				<point>78.000000,267.000000</point>
				<point>79.000000,259.000000</point>
				<point>98.000000,261.000000</point>
			</points>
		</object>
		<object>
			<coordinate>pixel</coordinate>
			<type>rectangle</type>
			<description>None</description>
			<possibleresult>
				<name>Van</name>
			</possibleresult>
			<points>
				<point>83.000000,106.000000</point>
				<point>80.000000,124.000000</point>
				<point>71.000000,122.000000</point>
				<point>74.000000,105.000000</point>
				<point>83.000000,106.000000</point>
			</points>
		</object>
		<object>
			<coordinate>pixel</coordinate>
			<type>rectangle</type>
			<description>None</description>
			<possibleresult>
				<name>Van</name>
			</possibleresult>
			<points>
				<point>58.000000,104.000000</point>
				<point>55.000000,121.000000</point>
				<point>46.000000,119.000000</point>
				<point>49.000000,103.000000</point>
				<point>58.000000,104.000000</point>
			</points>
		</object>
		<object>
			<coordinate>pixel</coordinate>
			<type>rectangle</type>
			<description>None</description>
			<possibleresult>
				<name>Van</name>
			</possibleresult>
			<points>
				<point>14.000000,98.000000</point>
				<point>10.000000,114.000000</point>
				<point>1.000000,112.000000</point>
				<point>4.000000,96.000000</point>
				<point>14.000000,98.000000</point>
			</points>
		</object>
		<object>
			<coordinate>pixel</coordinate>
			<type>rectangle</type>
			<description>None</description>
			<possibleresult>
				<name>Van</name>
			</possibleresult>
			<points>
				<point>116.000000,161.000000</point>
				<point>115.000000,169.000000</point>
				<point>94.000000,166.000000</point>
				<point>96.000000,158.000000</point>
				<point>116.000000,161.000000</point>
			</points>
		</object>
	</objects>
</annotation>